AUTHORS.rst
CONTRIBUTING.rst
HISTORY.rst
LICENSE
MANIFEST.in
README.md
pyproject.toml
setup.cfg
src/fussballgott/__init__.py
src/fussballgott/fussball.py
src/fussballgott/league.py
src/fussballgott/load.py
src/fussballgott/plot.py
src/fussballgott/team.py
src/fussballgott/tournament.py
src/fussballgott.egg-info/PKG-INFO
src/fussballgott.egg-info/SOURCES.txt
src/fussballgott.egg-info/dependency_links.txt
src/fussballgott.egg-info/not-zip-safe
src/fussballgott.egg-info/requires.txt
src/fussballgott.egg-info/top_level.txt
tests/test_fussballgott.py