Metadata-Version: 2.1
Name: fussballgott
Version: 0.1.0
Summary: Code to run simulations of football games, leagues and tournaments
Author: Silvan Fischbacher
Author-email: silvan.fischbacher@greenmail.ch
License: MIT License
Project-URL: Source, https://cosmo-docs.phys.ethz.ch/fussballgott
Classifier: Intended Audience :: Science/Research
Classifier: Intended Audience :: Developers
Classifier: License :: OSI Approved :: MIT License
Classifier: Natural Language :: English
Classifier: Programming Language :: Python :: 3
Classifier: Programming Language :: Python :: 3.9
Classifier: Programming Language :: Python :: 3.10
Classifier: Operating System :: OS Independent
Requires-Python: >=3.7
Provides-Extra: dev
Provides-Extra: docs
License-File: LICENSE
License-File: AUTHORS.rst
